reface_example_proto/__init__.py
reface_example_proto/recommender/__init__.py
reface_example_proto/recommender/v1/__init__.py
reface_example_proto/recommender/v1/tag_to_tag_service_pb2.py
reface_example_proto/recommender/v1/tag_to_tag_service_pb2.pyi
reface_example_proto/recommender/v1/tag_to_tag_service_pb2_grpc.py
reface_example_proto/recommender/v1/tag_to_tag_service_pb2_grpc.pyi
reface_example_proto-0.0.1.dist-info/METADATA
reface_example_proto-0.0.1.dist-info/WHEEL
reface_example_proto-0.0.1.dist-info/top_level.txt
reface_example_proto-0.0.1.dist-info/RECORD
